{
	"name": "Stage1_2_3_SalesPerson",
	"properties": {
		"activities": [
			{
				"name": "Stage1_SalesPerson_Master",
				"type": "Copy",
				"dependsOn": [
					{
						"activity": "TableNameVar",
						"dependencyConditions": [
							"Succeeded"
						]
					}
				],
				"policy": {
					"timeout": "0.12:00:00",
					"retry": 0,
					"retryIntervalInSeconds": 30,
					"secureOutput": false,
					"secureInput": false
				},
				"userProperties": [],
				"typeProperties": {
					"source": {
						"type": "SqlServerSource",
						"sqlReaderQuery": "with Salesperson_Purchaser_cte\tas \r\n(\r\nSelect \r\n\t[Code],\r\n\t[Name],\r\n\t[A_S_M_],\r\n\t[Agent],\r\n\t[ARM],\r\n\t[Location Code],\r\n\t[Route],\r\n\t[Sales hierarchy code],\r\n\t[Global Dimension 1 Code],\r\n\t[Zone],\r\n\t'10001' as Site_Code\r\nFROM [dbo].[BIPL - ANDHRA PRADESH$Salesperson_Purchaser]\r\nUNION ALL\r\nSelect \r\n\t[Code],\r\n\t[Name],\r\n\t[A_S_M_],\r\n\t[Agent],\r\n\t[ARM],\r\n\t[Location Code],\r\n\t[Route],\r\n\t[Sales hierarchy code],\r\n\t[Global Dimension 1 Code],\r\n\t[Zone],\r\n\t'10002' as Site_Code\r\nFROM [dbo].[BIPL - CHENNAI$Salesperson_Purchaser]\r\nUNION ALL\r\nSelect \r\n[Code],\r\n[Name],\r\n[A_S_M_],\r\n[Agent],\r\n[ARM],\r\n[Location Code],\r\n[Route],\r\n[Sales hierarchy code],\r\n[Global Dimension 1 Code],\r\n[Zone],\r\n'10003' as Site_Code\r\nFROM [dbo].[BIPL - CHHATTISGARH$Salesperson_Purchaser]\r\nUNION ALL\r\nSelect\r\n[Code],\r\n[Name],\r\n[A_S_M_],\r\n[Agent],\r\n[ARM],\r\n[Location Code],\r\n[Route],\r\n[Sales hierarchy code],\r\n[Global Dimension 1 Code],\r\n[Zone],\r\n'10004' as Site_Code\r\nFROM [dbo].[BIPL - DELHI$Salesperson_Purchaser]\r\nUNION ALL\r\nSelect\r\n[Code],\r\n[Name],\r\n[A_S_M_],\r\n[Agent],\r\n[ARM],\r\n[Location Code],\r\n[Route],\r\n[Sales hierarchy code],\r\n[Global Dimension 1 Code],\r\n[Zone],\r\n'10005' as Site_Code\r\nFROM [dbo].[BIPL - GOA$Salesperson_Purchaser]\r\nUNION ALL\r\nSelect\r\n[Code],\r\n[Name],\r\n[A_S_M_],\r\n[Agent],\r\n[ARM],\r\n[Location Code],\r\n[Route],\r\n[Sales hierarchy code],\r\n[Global Dimension 1 Code],\r\n[Zone],\r\n'10006' as Site_Code\r\nFROM [dbo].[BIPL - GUJARAT$Salesperson_Purchaser]\r\nUNION ALL\r\nSelect\r\n[Code],\r\n[Name],\r\n[A_S_M_],\r\n[Agent],\r\n[ARM],\r\n[Location Code],\r\n[Route],\r\n[Sales hierarchy code],\r\n[Global Dimension 1 Code],\r\n[Zone],\r\n'10006' as Site_Code\r\nFROM [dbo].[BIPL - HARYANA$Salesperson_Purchaser]\r\nUNION ALL\r\nSelect\r\n[Code],\r\n[Name],\r\n[A_S_M_],\r\n[Agent],\r\n[ARM],\r\n[Location Code],\r\n[Route],\r\n[Sales hierarchy code],\r\n[Global Dimension 1 Code],\r\n[Zone],\r\n'10009' as Site_Code\r\nFROM [dbo].[BIPL - JAIPUR$Salesperson_Purchaser]\r\nUNION ALL\r\nSelect\r\n[Code],\r\n[Name],\r\n[A_S_M_],\r\n[Agent],\r\n[ARM],\r\n[Location Code],\r\n[Route],\r\n[Sales hierarchy code],\r\n[Global Dimension 1 Code],\r\n[Zone],\r\n'10010' as Site_Code\r\nFROM [dbo].[BIPL - KAMSHET$Salesperson_Purchaser]\r\nUNION ALL\r\nSelect\r\n[Code],\r\n[Name],\r\n[A_S_M_],\r\n[Agent],\r\n[ARM],\r\n[Location Code],\r\n[Route],\r\n[Sales hierarchy code],\r\n[Global Dimension 1 Code],\r\n[Zone],\r\n'10011' as Site_Code\r\nFROM [dbo].[BIPL - KARNATAKA$Salesperson_Purchaser]\r\nUNION ALL\r\nSelect\r\n[Code],\r\n[Name],\r\n[A_S_M_],\r\n[Agent],\r\n[ARM],\r\n[Location Code],\r\n[Route],\r\n[Sales hierarchy code],\r\n[Global Dimension 1 Code],\r\n[Zone],\r\n'10012' as Site_Code\r\nFROM [dbo].[BIPL - KERALA$Salesperson_Purchaser]\r\nUNION ALL\r\nSelect\r\n[Code],\r\n[Name],\r\n[A_S_M_],\r\n[Agent],\r\n[ARM],\r\n[Location Code],\r\n[Route],\r\n[Sales hierarchy code],\r\n[Global Dimension 1 Code],\r\n[Zone],\r\n'10013' as Site_Code\r\nFROM [dbo].[BIPL - MADHYAPRADESH$Salesperson_Purchaser]\r\nUNION ALL\r\nSelect\r\n[Code],\r\n[Name],\r\n[A_S_M_],\r\n[Agent],\r\n[ARM],\r\n[Location Code],\r\n[Route],\r\n[Sales hierarchy code],\r\n[Global Dimension 1 Code],\r\n[Zone],\r\n'10014' as Site_Code\r\nFROM [dbo].[BIPL - MUMBAI$Salesperson_Purchaser]\r\nUNION ALL\r\nSelect\r\n[Code],\r\n[Name],\r\n[A_S_M_],\r\n[Agent],\r\n[ARM],\r\n[Location Code],\r\n[Route],\r\n[Sales hierarchy code],\r\n[Global Dimension 1 Code],\r\n[Zone],\r\n'10015' as Site_Code\r\nFROM [dbo].[BIPL - ODISHA$Salesperson_Purchaser]\r\nUNION ALL\r\nSelect\r\n[Code],\r\n[Name],\r\n[A_S_M_],\r\n[Agent],\r\n[ARM],\r\n[Location Code],\r\n[Route],\r\n[Sales hierarchy code],\r\n[Global Dimension 1 Code],\r\n[Zone],\r\n'10016' as Site_Code\r\nFROM [dbo].[BIPL - PUNE$Salesperson_Purchaser]\r\nUNION ALL\r\nSelect\r\n[Code],\r\n[Name],\r\n[A_S_M_],\r\n[Agent],\r\n[ARM],\r\n[Location Code],\r\n[Route],\r\n[Sales hierarchy code],\r\n[Global Dimension 1 Code],\r\n[Zone],\r\n'10017' as Site_Code\r\nFROM [dbo].[BIPL - PUNJAB$Salesperson_Purchaser]\r\nUNION ALL\r\nSelect\r\n[Code],\r\n[Name],\r\n[A_S_M_],\r\n[Agent],\r\n[ARM],\r\n[Location Code],\r\n[Route],\r\n[Sales hierarchy code],\r\n[Global Dimension 1 Code],\r\n[Zone],\r\n'10018' as Site_Code\r\nFROM [dbo].[BIPL - RUDRAPUR$Salesperson_Purchaser]\r\nUNION ALL\r\nSelect\r\n[Code],\r\n[Name],\r\n[A_S_M_],\r\n[Agent],\r\n[ARM],\r\n[Location Code],\r\n[Route],\r\n[Sales hierarchy code],\r\n[Global Dimension 1 Code],\r\n[Zone],\r\n'10019' as Site_Code\r\nFROM [dbo].[BIPL – SAHIBABAD$Salesperson_Purchaser]\r\nUNION ALL\r\nSelect\r\n[Code],\r\n[Name],\r\n[A_S_M_],\r\n[Agent],\r\n[ARM],\r\n[Location Code],\r\n[Route],\r\n[Sales hierarchy code],\r\n[Global Dimension 1 Code],\r\n[Zone],\r\n'10020' as Site_Code\r\nFROM [dbo].[BIPL - TELANGANA$Salesperson_Purchaser]\r\nUNION ALL\r\nSelect\r\n[Code],\r\n[Name],\r\n[A_S_M_],\r\n[Agent],\r\n[ARM],\r\n[Location Code],\r\n[Route],\r\n[Sales hierarchy code],\r\n[Global Dimension 1 Code],\r\n[Zone],\r\n'10021' as Site_Code\r\nFROM [dbo].[BIPL - WESTBENGAL$Salesperson_Purchaser]\r\n),\r\nSales_hierarchy_cte as \r\n(\r\nSelect\r\n[Territory Code],\r\n[Area Code],\r\n[Branch Code],\r\n[Zone Code],\r\n[National Code],\r\n[National Name],\r\n[Region Code],\r\n[Region Name],\r\n[Regional Sales Head Name],\r\n[Branch Name],\r\n[Branch Sales Head Name],\r\n[Zone Name],\r\n[Sales Manager Name],\r\n[Area Name],\r\n[Area Sales Manager Name],\r\n[Territory Name],\r\n[Sales Executive Name],\r\n[Division Name],\r\n[SE Code],\r\n[Channel],\r\n[Business Unit],\r\n'10001' as Site_Code\r\nFROM [dbo].[BIPL - ANDHRA PRADESH$Sales hierarchy]\r\nUNION ALL\r\nSelect\r\n[Territory Code],\r\n[Area Code],\r\n[Branch Code],\r\n[Zone Code],\r\n[National Code],\r\n[National Name],\r\n[Region Code],\r\n[Region Name],\r\n[Regional Sales Head Name],\r\n[Branch Name],\r\n[Branch Sales Head Name],\r\n[Zone Name],\r\n[Sales Manager Name],\r\n[Area Name],\r\n[Area Sales Manager Name],\r\n[Territory Name],\r\n[Sales Executive Name],\r\n[Division Name],\r\n[SE Code],\r\n[Channel],\r\n[Business Unit],\r\n'10002' as Site_Code\r\nFROM [dbo].[BIPL - CHENNAI$Sales hierarchy]\r\nUNION ALL\r\nSelect\r\n[Territory Code],\r\n[Area Code],\r\n[Branch Code],\r\n[Zone Code],\r\n[National Code],\r\n[National Name],\r\n[Region Code],\r\n[Region Name],\r\n[Regional Sales Head Name],\r\n[Branch Name],\r\n[Branch Sales Head Name],\r\n[Zone Name],\r\n[Sales Manager Name],\r\n[Area Name],\r\n[Area Sales Manager Name],\r\n[Territory Name],\r\n[Sales Executive Name],\r\n[Division Name],\r\n[SE Code],\r\n[Channel],\r\n[Business Unit],\r\n'10003' as Site_Code\r\nFROM [dbo].[BIPL - CHHATTISGARH$Sales hierarchy]\r\nUNION ALL\r\nSelect\r\n[Territory Code],\r\n[Area Code],\r\n[Branch Code],\r\n[Zone Code],\r\n[National Code],\r\n[National Name],\r\n[Region Code],\r\n[Region Name],\r\n[Regional Sales Head Name],\r\n[Branch Name],\r\n[Branch Sales Head Name],\r\n[Zone Name],\r\n[Sales Manager Name],\r\n[Area Name],\r\n[Area Sales Manager Name],\r\n[Territory Name],\r\n[Sales Executive Name],\r\n[Division Name],\r\n[SE Code],\r\n[Channel],\r\n[Business Unit],\r\n'10004' as Site_Code\r\nFROM [dbo].[BIPL - DELHI$Sales hierarchy]\r\nUNION ALL\r\nSelect\r\n[Territory Code],\r\n[Area Code],\r\n[Branch Code],\r\n[Zone Code],\r\n[National Code],\r\n[National Name],\r\n[Region Code],\r\n[Region Name],\r\n[Regional Sales Head Name],\r\n[Branch Name],\r\n[Branch Sales Head Name],\r\n[Zone Name],\r\n[Sales Manager Name],\r\n[Area Name],\r\n[Area Sales Manager Name],\r\n[Territory Name],\r\n[Sales Executive Name],\r\n[Division Name],\r\n[SE Code],\r\n[Channel],\r\n[Business Unit],\r\n'10005' as Site_Code\r\nFROM [dbo].[BIPL - GOA$Sales hierarchy]\r\nUNION ALL\r\nSelect\r\n[Territory Code],\r\n[Area Code],\r\n[Branch Code],\r\n[Zone Code],\r\n[National Code],\r\n[National Name],\r\n[Region Code],\r\n[Region Name],\r\n[Regional Sales Head Name],\r\n[Branch Name],\r\n[Branch Sales Head Name],\r\n[Zone Name],\r\n[Sales Manager Name],\r\n[Area Name],\r\n[Area Sales Manager Name],\r\n[Territory Name],\r\n[Sales Executive Name],\r\n[Division Name],\r\n[SE Code],\r\n[Channel],\r\n[Business Unit],\r\n'10006' as Site_Code\r\nFROM [dbo].[BIPL - GUJARAT$Sales hierarchy]\r\nUNION ALL\r\nSelect\r\n[Territory Code],\r\n[Area Code],\r\n[Branch Code],\r\n[Zone Code],\r\n[National Code],\r\n[National Name],\r\n[Region Code],\r\n[Region Name],\r\n[Regional Sales Head Name],\r\n[Branch Name],\r\n[Branch Sales Head Name],\r\n[Zone Name],\r\n[Sales Manager Name],\r\n[Area Name],\r\n[Area Sales Manager Name],\r\n[Territory Name],\r\n[Sales Executive Name],\r\n[Division Name],\r\n[SE Code],\r\n[Channel],\r\n[Business Unit],\r\n'10007' as Site_Code\r\nFROM [dbo].[BIPL - HARYANA$Sales hierarchy]\r\nUNION ALL\r\nSelect\r\n[Territory Code],\r\n[Area Code],\r\n[Branch Code],\r\n[Zone Code],\r\n[National Code],\r\n[National Name],\r\n[Region Code],\r\n[Region Name],\r\n[Regional Sales Head Name],\r\n[Branch Name],\r\n[Branch Sales Head Name],\r\n[Zone Name],\r\n[Sales Manager Name],\r\n[Area Name],\r\n[Area Sales Manager Name],\r\n[Territory Name],\r\n[Sales Executive Name],\r\n[Division Name],\r\n[SE Code],\r\n[Channel],\r\n[Business Unit],\r\n'10009' as Site_Code\r\nFROM [dbo].[BIPL - JAIPUR$Sales hierarchy]\r\nUNION ALL\r\nSelect\r\n[Territory Code],\r\n[Area Code],\r\n[Branch Code],\r\n[Zone Code],\r\n[National Code],\r\n[National Name],\r\n[Region Code],\r\n[Region Name],\r\n[Regional Sales Head Name],\r\n[Branch Name],\r\n[Branch Sales Head Name],\r\n[Zone Name],\r\n[Sales Manager Name],\r\n[Area Name],\r\n[Area Sales Manager Name],\r\n[Territory Name],\r\n[Sales Executive Name],\r\n[Division Name],\r\n[SE Code],\r\n[Channel],\r\n[Business Unit],\r\n'10010' as Site_Code\r\nFROM [dbo].[BIPL - KAMSHET$Sales hierarchy]\r\nUNION ALL\r\nSelect\r\n[Territory Code],\r\n[Area Code],\r\n[Branch Code],\r\n[Zone Code],\r\n[National Code],\r\n[National Name],\r\n[Region Code],\r\n[Region Name],\r\n[Regional Sales Head Name],\r\n[Branch Name],\r\n[Branch Sales Head Name],\r\n[Zone Name],\r\n[Sales Manager Name],\r\n[Area Name],\r\n[Area Sales Manager Name],\r\n[Territory Name],\r\n[Sales Executive Name],\r\n[Division Name],\r\n[SE Code],\r\n[Channel],\r\n[Business Unit],\r\n'10011' as Site_Code\r\nFROM [dbo].[BIPL - KARNATAKA$Sales hierarchy]\r\nUNION ALL\r\nSelect\r\n[Territory Code],\r\n[Area Code],\r\n[Branch Code],\r\n[Zone Code],\r\n[National Code],\r\n[National Name],\r\n[Region Code],\r\n[Region Name],\r\n[Regional Sales Head Name],\r\n[Branch Name],\r\n[Branch Sales Head Name],\r\n[Zone Name],\r\n[Sales Manager Name],\r\n[Area Name],\r\n[Area Sales Manager Name],\r\n[Territory Name],\r\n[Sales Executive Name],\r\n[Division Name],\r\n[SE Code],\r\n[Channel],\r\n[Business Unit],\r\n'10012' as Site_Code\r\nFROM [dbo].[BIPL - KERALA$Sales hierarchy]\r\nUNION ALL\r\nSelect\r\n[Territory Code],\r\n[Area Code],\r\n[Branch Code],\r\n[Zone Code],\r\n[National Code],\r\n[National Name],\r\n[Region Code],\r\n[Region Name],\r\n[Regional Sales Head Name],\r\n[Branch Name],\r\n[Branch Sales Head Name],\r\n[Zone Name],\r\n[Sales Manager Name],\r\n[Area Name],\r\n[Area Sales Manager Name],\r\n[Territory Name],\r\n[Sales Executive Name],\r\n[Division Name],\r\n[SE Code],\r\n[Channel],\r\n[Business Unit],\r\n'10013' as Site_Code\r\nFROM [dbo].[BIPL - MADHYAPRADESH$Sales hierarchy]\r\nUNION ALL\r\nSelect\r\n[Territory Code],\r\n[Area Code],\r\n[Branch Code],\r\n[Zone Code],\r\n[National Code],\r\n[National Name],\r\n[Region Code],\r\n[Region Name],\r\n[Regional Sales Head Name],\r\n[Branch Name],\r\n[Branch Sales Head Name],\r\n[Zone Name],\r\n[Sales Manager Name],\r\n[Area Name],\r\n[Area Sales Manager Name],\r\n[Territory Name],\r\n[Sales Executive Name],\r\n[Division Name],\r\n[SE Code],\r\n[Channel],\r\n[Business Unit],\r\n'10014' as Site_Code\r\nFROM [dbo].[BIPL - MUMBAI$Sales hierarchy]\r\nUNION ALL\r\nSelect\r\n[Territory Code],\r\n[Area Code],\r\n[Branch Code],\r\n[Zone Code],\r\n[National Code],\r\n[National Name],\r\n[Region Code],\r\n[Region Name],\r\n[Regional Sales Head Name],\r\n[Branch Name],\r\n[Branch Sales Head Name],\r\n[Zone Name],\r\n[Sales Manager Name],\r\n[Area Name],\r\n[Area Sales Manager Name],\r\n[Territory Name],\r\n[Sales Executive Name],\r\n[Division Name],\r\n[SE Code],\r\n[Channel],\r\n[Business Unit],\r\n'10015' as Site_Code\r\nFROM [dbo].[BIPL - ODISHA$Sales hierarchy]\r\nUNION ALL\r\nSelect\r\n[Territory Code],\r\n[Area Code],\r\n[Branch Code],\r\n[Zone Code],\r\n[National Code],\r\n[National Name],\r\n[Region Code],\r\n[Region Name],\r\n[Regional Sales Head Name],\r\n[Branch Name],\r\n[Branch Sales Head Name],\r\n[Zone Name],\r\n[Sales Manager Name],\r\n[Area Name],\r\n[Area Sales Manager Name],\r\n[Territory Name],\r\n[Sales Executive Name],\r\n[Division Name],\r\n[SE Code],\r\n[Channel],\r\n[Business Unit],\r\n'10016' as Site_Code\r\nFROM [dbo].[BIPL - PUNE$Sales hierarchy]\r\nUNION ALL\r\nSelect\r\n[Territory Code],\r\n[Area Code],\r\n[Branch Code],\r\n[Zone Code],\r\n[National Code],\r\n[National Name],\r\n[Region Code],\r\n[Region Name],\r\n[Regional Sales Head Name],\r\n[Branch Name],\r\n[Branch Sales Head Name],\r\n[Zone Name],\r\n[Sales Manager Name],\r\n[Area Name],\r\n[Area Sales Manager Name],\r\n[Territory Name],\r\n[Sales Executive Name],\r\n[Division Name],\r\n[SE Code],\r\n[Channel],\r\n[Business Unit],\r\n'10017' as Site_Code\r\nFROM [dbo].[BIPL - PUNJAB$Sales hierarchy]\r\nUNION ALL\r\nSelect\r\n[Territory Code],\r\n[Area Code],\r\n[Branch Code],\r\n[Zone Code],\r\n[National Code],\r\n[National Name],\r\n[Region Code],\r\n[Region Name],\r\n[Regional Sales Head Name],\r\n[Branch Name],\r\n[Branch Sales Head Name],\r\n[Zone Name],\r\n[Sales Manager Name],\r\n[Area Name],\r\n[Area Sales Manager Name],\r\n[Territory Name],\r\n[Sales Executive Name],\r\n[Division Name],\r\n[SE Code],\r\n[Channel],\r\n[Business Unit],\r\n'10018' as Site_Code\r\nFROM [dbo].[BIPL - RUDRAPUR$Sales hierarchy]\r\nUNION ALL\r\nSelect\r\n\t[Territory Code],\r\n\t[Area Code],\r\n\t[Branch Code],\r\n\t[Zone Code],\r\n\t[National Code],\r\n\t[National Name],\r\n\t[Region Code],\r\n\t[Region Name],\r\n\t[Regional Sales Head Name],\r\n\t[Branch Name],\r\n\t[Branch Sales Head Name],\r\n\t[Zone Name],\r\n\t[Sales Manager Name],\r\n\t[Area Name],\r\n\t[Area Sales Manager Name],\r\n\t[Territory Name],\r\n\t[Sales Executive Name],\r\n\t[Division Name],\r\n\t[SE Code],\r\n\t[Channel],\r\n\t[Business Unit],\r\n\t'10019' as Site_Code\r\nFROM [dbo].[BIPL – SAHIBABAD$Sales hierarchy]\r\nUNION ALL\r\nSelect\r\n\t[Territory Code],\r\n\t[Area Code],\r\n\t[Branch Code],\r\n\t[Zone Code],\r\n\t[National Code],\r\n\t[National Name],\r\n\t[Region Code],\r\n\t[Region Name],\r\n\t[Regional Sales Head Name],\r\n\t[Branch Name],\r\n\t[Branch Sales Head Name],\r\n\t[Zone Name],\r\n\t[Sales Manager Name],\r\n\t[Area Name],\r\n\t[Area Sales Manager Name],\r\n\t[Territory Name],\r\n\t[Sales Executive Name],\r\n\t[Division Name],\r\n\t[SE Code],\r\n\t[Channel],\r\n\t[Business Unit],\r\n\t'10020' as Site_Code\r\nFROM [dbo].[BIPL - TELANGANA$Sales hierarchy]\r\nUNION ALL\r\nSelect\r\n\t[Territory Code],\r\n\t[Area Code],\r\n\t[Branch Code],\r\n\t[Zone Code],\r\n\t[National Code],\r\n\t[National Name],\r\n\t[Region Code],\r\n\t[Region Name],\r\n\t[Regional Sales Head Name],\r\n\t[Branch Name],\r\n\t[Branch Sales Head Name],\r\n\t[Zone Name],\r\n\t[Sales Manager Name],\r\n\t[Area Name],\r\n\t[Area Sales Manager Name],\r\n\t[Territory Name],\r\n\t[Sales Executive Name],\r\n\t[Division Name],\r\n\t[SE Code],\r\n\t[Channel],\r\n\t[Business Unit],\r\n\t'10021' as Site_Code\r\nFROM [dbo].[BIPL - WESTBENGAL$Sales hierarchy]\r\n),\r\nLeft_join_cte as \r\n(\r\nSelect \r\n\t--sp\r\n\tsp.[Code],\r\n\tsp.[Name],\r\n\tsp.[A_S_M_],\r\n\tsp.[Agent],\r\n\tsp.[ARM],\r\n\tsp.[Location Code],\r\n\tsp.[Route],\r\n\tsp.[Sales hierarchy code],\r\n\tsp.[Global Dimension 1 Code],\r\n\tsp.[Zone],\r\n\tsp.Site_Code,\r\n\r\n\t--sh\r\n\tsh.[Sales Executive Name],\r\n\tsh.[Sales Manager Name],\r\n\tsh.[Area Sales Manager Name],\r\n\tsh.[Branch Sales Head Name],\r\n\tsh.[Regional Sales Head Name],\r\n\r\n\t--GEO\r\n\tsh.[Area Code],\r\n\tsh.[Area Name],\r\n\tsh.[Branch Code],\r\n\tsh.[Branch Name],\r\n\tsh.[Territory Code],\r\n\tsh.[Territory Name],\r\n\tsh.[Region Code],\r\n\tsh.[Region Name],\r\n\tsh.[Zone Code],\r\n\tsh.[Zone Name],\r\n\tsh.[National Code],\r\n\tsh.[National Name],\r\n\tsh.[Division Name]\r\n\r\n\t--concat(sp.Site_Code,'|', sp.[Sales hierarchy code]) as sp_key,\r\n\t--concat(sh.Site_Code,'|', sh.[Territory Code]) as sh_key\r\nfrom \r\n\tSalesperson_Purchaser_cte as sp\r\nleft join\r\n\tSales_hierarchy_cte as sh\r\non\r\nsp.[Sales hierarchy code] = sh.[Territory Code]) and sp.Site_Code = sh.Site_Code\t\r\n)\r\nSelect \r\n\t*\r\nfrom \r\n\tLeft_join_cte\r\n",
						"queryTimeout": "02:00:00",
						"partitionOption": "None"
					},
					"sink": {
						"type": "DelimitedTextSink",
						"storeSettings": {
							"type": "AzureBlobFSWriteSettings"
						},
						"formatSettings": {
							"type": "DelimitedTextWriteSettings",
							"quoteAllText": true,
							"fileExtension": ".txt"
						}
					},
					"enableStaging": false,
					"translator": {
						"type": "TabularTranslator",
						"typeConversion": true,
						"typeConversionSettings": {
							"allowDataTruncation": true,
							"treatBooleanAsNumber": false
						}
					}
				},
				"inputs": [
					{
						"referenceName": "Stage1_SalesPerson_Source",
						"type": "DatasetReference"
					}
				],
				"outputs": [
					{
						"referenceName": "Stage1_SalesPerson_Sink",
						"type": "DatasetReference",
						"parameters": {
							"FileName": {
								"value": "@variables('TableName')",
								"type": "Expression"
							}
						}
					}
				]
			},
			{
				"name": "FileName",
				"type": "Lookup",
				"dependsOn": [],
				"policy": {
					"timeout": "0.12:00:00",
					"retry": 0,
					"retryIntervalInSeconds": 30,
					"secureOutput": false,
					"secureInput": false
				},
				"userProperties": [],
				"typeProperties": {
					"source": {
						"type": "SqlServerSource",
						"sqlReaderQuery": "Select \n\tDistinct\n\tLeft(RIGHT(TABLE_NAME, 21),11) as TABLE_NAME\nfrom INFORMATION_SCHEMA.COLUMNS\nwhere TABLE_NAME like '%Salesperson_Purchaser'",
						"queryTimeout": "02:00:00",
						"partitionOption": "None"
					},
					"dataset": {
						"referenceName": "Stage1_SalesPerson_Source",
						"type": "DatasetReference"
					}
				}
			},
			{
				"name": "TableNameVar",
				"type": "SetVariable",
				"dependsOn": [
					{
						"activity": "FileName",
						"dependencyConditions": [
							"Succeeded"
						]
					}
				],
				"userProperties": [],
				"typeProperties": {
					"variableName": "TableName",
					"value": {
						"value": "@activity('FileName').output.firstRow.TABLE_NAME",
						"type": "Expression"
					}
				}
			}
		],
		"variables": {
			"TableName": {
				"type": "String"
			}
		},
		"annotations": []
	}
}